{"cookies": [], "origins": [{"origin": "https://nikita-filonov.github.io", "localStorage": [{"name": "persist:users", "value": "{\"user\":\"{\\\"id\\\":\\\"abbedf09-85b8-4170-a72e-75fda7649856\\\",\\\"email\\\":\\\"test@test.com\\\",\\\"username\\\":\\\"test_user\\\",\\\"password\\\":\\\"test_password\\\"}\",\"users\":\"[{\\\"id\\\":\\\"abbedf09-85b8-4170-a72e-75fda7649856\\\",\\\"email\\\":\\\"test@test.com\\\",\\\"username\\\":\\\"test_user\\\",\\\"password\\\":\\\"test_password\\\"}]\",\"_persist\":\"{\\\"version\\\":-1,\\\"rehydrated\\\":true}\"}"}, {"name": "persist:courses", "value": "{\"course\":\"{\\\"id\\\":\\\"\\\",\\\"title\\\":\\\"\\\",\\\"userId\\\":\\\"\\\",\\\"maxScore\\\":0,\\\"minScore\\\":0,\\\"exercises\\\":[],\\\"description\\\":\\\"\\\",\\\"previewImage\\\":null,\\\"estimatedTime\\\":\\\"\\\"}\",\"courses\":\"[]\",\"_persist\":\"{\\\"version\\\":-1,\\\"rehydrated\\\":true}\"}"}]}]}